README.md
setup.py
atnlp/__init__.py
atnlp.egg-info/PKG-INFO
atnlp.egg-info/SOURCES.txt
atnlp.egg-info/dependency_links.txt
atnlp.egg-info/requires.txt
atnlp.egg-info/top_level.txt
atnlp/core/__init__.py
atnlp/core/helpers.py
atnlp/core/logger.py
atnlp/core/setup.py
atnlp/data/__init__.py
atnlp/data/io.py
atnlp/data/parse.py
atnlp/data/reuters.py
atnlp/eval/__init__.py
atnlp/eval/html.py
atnlp/eval/keras.py
atnlp/eval/metrics.py
atnlp/eval/plot.py
atnlp/eval/table.py
atnlp/model/__init__.py
atnlp/model/embed.py
atnlp/model/grid.py
atnlp/model/io.py
atnlp/model/tune.py
atnlp/model/wordmatch.py
atnlp/share/config/logreg.yml
atnlp/share/config/svm.yml
atnlp/share/config/wordmatch.yml
atnlp/share/models/logreg.py
atnlp/share/models/svm.py
atnlp/share/models/wordmatch.py
scripts/evaluate.py
scripts/install_glove.py
scripts/predict.py
scripts/print_modules.py
scripts/start_jupyter.sh
scripts/summary.py
scripts/train.py
scripts/reuters/install_reuters.py
scripts/reuters/make_grid.py
scripts/reuters/reuters_to_txt.py
scripts/reuters/train_reuters_rnn.py