Metadata-Version: 2.1
Name: atnlp
Version: 0.0.11
Summary: A tool for natural language processing in python based on scipy and sklearn
Home-page: https://github.com/wedavey/atnlp
Author: Will Davey
Author-email: wedavey@gmail.com
License: MIT
Platform: UNKNOWN
Classifier: Programming Language :: Python :: 3
Classifier: License :: OSI Approved :: MIT License
Classifier: Operating System :: OS Independent
Classifier: Natural Language :: English
Classifier: Topic :: Scientific/Engineering :: Information Analysis
Classifier: Topic :: Scientific/Engineering :: Artificial Intelligence
Requires-Python: >=3.5
Provides-Extra: deep
Provides-Extra: book
Provides-Extra: extras
Provides-Extra: docs
Provides-Extra: dev
